tfaug.py
tfaug-0.1.0.5.dist-info/LICENSE
tfaug-0.1.0.5.dist-info/METADATA
tfaug-0.1.0.5.dist-info/WHEEL
tfaug-0.1.0.5.dist-info/top_level.txt
tfaug-0.1.0.5.dist-info/RECORD
