Metadata-Version: 2.1
Name: tfaug
Version: 0.1.0.5
Summary: tensorflow easy image augmantation
Home-page: https://github.com/piyop/tfaug
Author: piyop
Author-email: t.okuda@keio.com
License: MIT
Platform: UNKNOWN
Classifier: Programming Language :: Python :: 3
Classifier: License :: OSI Approved :: MIT License
Classifier: Operating System :: OS Independent
Requires-Python: >=3.4
Requires-Dist: tensorflow (>=2.0)
Requires-Dist: tensorflow-addons (>=0.7.1)
